stellarmesh/__init__.py
stellarmesh/_core.py
stellarmesh/geometry.py
stellarmesh/mesh.py
stellarmesh/moab.py
stellarmesh-1.1.0.dist-info/licenses/LICENSE
stellarmesh-1.1.0.dist-info/METADATA
stellarmesh-1.1.0.dist-info/WHEEL
stellarmesh-1.1.0.dist-info/top_level.txt
stellarmesh-1.1.0.dist-info/RECORD
